{
    "base": "https://assets.codistica.com/bin/dummy/",
    "files": {
        "20480": 30,
        "102400": 20,
        "204800": 20,
        "2097152": 20,
        "5242880": 10,
        "15728640": 5,
        "31457280": 5
    },
    "sizes": {
        "20480": {
            "identity": "20480",
            "gzip": "20515"
        },
        "102400": {
            "identity": "102400",
            "gzip": "102446"
        },
        "204800": {
            "identity": "204800",
            "gzip": "204856"
        },
        "2097152": {
            "identity": "2097152",
            "gzip": "2097404"
        },
        "5242880": {
            "identity": "5242880",
            "gzip": "5243457"
        },
        "15728640": {
            "identity": "15728640",
            "gzip": "15730308"
        },
        "31457280": {
            "identity": "31457280",
            "gzip": "31460583"
        }
    }
}
